pytest_console_scripts/__init__.py
pytest_console_scripts/py.typed
pytest_console_scripts-1.4.1.dist-info/LICENSE
pytest_console_scripts-1.4.1.dist-info/METADATA
pytest_console_scripts-1.4.1.dist-info/WHEEL
pytest_console_scripts-1.4.1.dist-info/entry_points.txt
pytest_console_scripts-1.4.1.dist-info/top_level.txt
pytest_console_scripts-1.4.1.dist-info/RECORD
