Metadata-Version: 2.1
Name: pytest-console-scripts
Version: 1.4.1
Summary: Pytest plugin for testing console scripts
Home-page: https://github.com/kvas-it/pytest-console-scripts
Author: Vasily Kuznetsov
Author-email: kvas.it@gmail.com
Maintainer: Vasily Kuznetsov, Kyle Benesch
Maintainer-email: kvas.it@gmail.com, 4b796c65+github@gmail.com
License: MIT
Classifier: Development Status :: 4 - Beta
Classifier: Framework :: Pytest
Classifier: Intended Audience :: Developers
Classifier: Topic :: Software Development :: Testing
Classifier: Programming Language :: Python
Classifier: Programming Language :: Python :: 3
Classifier: Programming Language :: Python :: 3.8
Classifier: Programming Language :: Python :: 3.9
Classifier: Programming Language :: Python :: 3.10
Classifier: Programming Language :: Python :: 3.11
Classifier: Programming Language :: Python :: Implementation :: CPython
Classifier: Programming Language :: Python :: Implementation :: PyPy
Classifier: Operating System :: OS Independent
Classifier: License :: OSI Approved :: MIT License
Requires-Python: >=3.8
License-File: LICENSE
Requires-Dist: pytest (>=4.0.0)
Requires-Dist: importlib-metadata (>=3.6) ; python_version < "3.10"
